Tarea2/reg_desp_32.v
`include "reg_desp.v"
`include "mux.v"

module reg_desp_32(Q32, S_OUT32, CLK32, ENB32, DIR32, S_IN32, MODO32, D32);

	//Declarando entradas y salidas
    input CLK32, ENB32, DIR32, S_IN32;
    input [1:0] MODO32;
    input [31:0] D32;
    output [31:0] Q32;
    output S_OUT32;
  //Declarando cables internos
    //Q's
    wire wR1Q0, wR1Q3, wR2Q0, wR2Q3, wR3Q0, wR3Q3, wR4Q0;
    wire wR4Q3, wR5Q0, wR5Q3, wR6Q0, wR6Q3, wR7Q0, wR7Q3;
    wire wR8Q0, wR8Q3;
    //S_IN's
    wire wR1SIN, wR2SIN, wR3SIN, wR4SIN, wR5SIN;
    wire wR6SIN, wR7SIN, wR8SIN;
    //Parametros registro 32 b
    wire wS_OUT32, wCLK32, wENB32, wDIR32, wS_IN32;
    wire [31:0] wQ32, wD32;
    wire [1:0] wMODO32;

  //Asignacion de los Cables
    //Salidas
    assign Q32[31:0] = wQ32[31:0];
    assign S_OUT32 = wS_OUT32;
    //Entradas
    assign wCLK32 = CLK32;
    assign wENB32 = ENB32;
    assign wDIR32 = DIR32;
    assign wS_IN32 = S_IN32;
    assign wMODO32 = MODO32;
    assign wD32 = D32;
    //Cables transferencia datos
    assign wR8Q0 = wQ8[0];
    assign wR8Q3 = wQ8[3];
    assign wR7Q0 = wQ8[4];
    assign wR7Q3 = wQ8[7];
    assign wR6Q0 = wQ8[8];
    assign wR6Q3 = wQ8[11];
    assign wR5Q0 = wQ8[12];
    assign wR5Q3 = wQ8[15];
    assign wR4Q0 = wQ8[16];
    assign wR4Q3 = wQ8[19];
    assign wR3Q0 = wQ8[20];
    assign wR3Q3 = wQ8[23];
    assign wR2Q0 = wQ8[24];
    assign wR2Q3 = wQ8[27];
    assign wR1Q0 = wQ8[28];
    assign wR1Q3 = wQ8[31];

 //Inicio registros (Registro1)
  mux mOUT(wR1Q3, wR8Q0, wDIR32, wS_OUT32);
	reg_desp reg1(wQ32[31:28], /*vacio*/, wCLK32, wENB32, wDIR32, wR1SIN, wMODO32, wD32[31:28]);
 //Intermedio (Registros 2 al 7)
  mux m1(wR2Q3, wS_IN32, wDIR32, wR1SIN);
  reg_desp reg2(wQ32[27:24], /*vacio*/, wCLK32, wENB32, wDIR32, wR2SIN, wMODO32, wD32[27:24]);
  mux m2(wR3Q3, wR1Q0, wDIR32, wR2SIN);
  reg_desp reg3(wQ32[23:20], /*vacio*/, wCLK32, wENB32, wDIR32, wR2SIN, wMODO32, wD32[23:20]);
  mux m3(wR4Q3, wR2Q0, wDIR32, wR3SIN);
  reg_desp reg4(wQ32[19:16], /*vacio*/, wCLK32, wENB32, wDIR32, wR2SIN, wMODO32, wD32[19:16]);
  mux m4(wR5Q3, wR3Q0, wDIR32, wR4SIN);
  reg_desp reg5(wQ32[15:12], /*vacio*/, wCLK32, wENB32, wDIR32, wR2SIN, wMODO32, wD32[15:12]);
  mux m5(wR6Q3, wR4Q0, wDIR32, wR5SIN);
  reg_desp reg6(wQ32[11:8], /*vacio*/, wCLK32, wENB32, wDIR32, wR2SIN, wMODO32, wD32[11:8]);
  mux m6(wR7Q3, wR5Q0, wDIR32, wR6SIN);
  reg_desp reg7(wQ32[7:4], /*vacio*/, wCLK32, wENB32, wDIR32, wR2SIN, wMODO32, wD32[7:4]);
  mux m7(wR8Q3, wR6Q0, wDIR32, wR7SIN);
  //Final registros (Registro8)
  reg_desp reg8(wQ32[3:0], /*vacio*/, wCLK32, wENB32, wDIR32, wR8SIN, wMODO32, wD32[3:0]);
  mux m8(wS_IN32, wR7Q0, wDIR32, wR8SIN);

endmodule

Tarea2/probador8.v
module probador8(Q, S_OUT, CLK, ENB, DIR, S_IN, MODO, D);

    output reg CLK, ENB, DIR, S_IN;
    output reg [1:0] MODO;
    output reg [7:0] D;
    input [7:0] Q;
    input S_OUT;

		initial begin
				CLK = 0;
		end

		always begin
				#1 CLK = ~CLK;
		end

	initial begin
		//Prueba #1 rotacion a la izquierda
		    //Habilita lectura del modo
			ENB <= 1'b1;
		    //Establece modo de Carga en Paralelo
		  #1 MODO[1:0] <= 2'b10;
			DIR <= 1'b0;
		  S_IN <= 1'b0;
			D <= 8'hF;
			//Pone modo de rotacion, como DIR=0 es a la izquierda
			#2 MODO[1:0] <= 2'b0;
      #1 ENB <= 1'b0;
			//Enviar 4 flancos activos en CLK, luego da otros flancos para percibir salida final de S_OUT
			#8 ;

		//Prueba #2 rotacion a la derecha
		    //Establece modo de Carga en Paralelo
      #1 ENB <= 1'b1;
		  #2 MODO[1:0] <= 2'b10;
			DIR <= 1'b1;
			S_IN <= 1'b1;
			D <= 8'hF;
			//Pone modo de rotacion, como DIR=1 es a la derecha
			#2 MODO[1:0] <= 2'b0;
      #1 ENB <= 1'b0;
			//Enviando flancos activos en CLK
			#8 ;

		//Prueba #3 rotacion circular a la izquierda
		    //Establece modo de Carga en Paralelo
      #1 ENB <= 1'b1;
      #2 MODO[1:0] <= 2'b10;
			DIR <= 1'b0;
			S_IN <= 1'b1;
			D <= 8'hF0;
			//Pone modo de rotacion, como DIR=0 es a la izquierda
			#2 MODO[1:0] <= 2'b01;
      #1 ENB <= 1'b0;
			//Enviando flancos activos en CLK
			#8 ;

        //Prueba #4 rotacion circular a la derecha
		    //Establece modo de Carga en Paralelo
      #1 ENB <= 1'b1;
  		#2 MODO[1:0] <= 2'b10;
			DIR <= 1'b1;
			S_IN <= 1'b1;
			D <= 8'h0F;
			//Pone modo de rotacion, como DIR=1 es a la derecha
			#2 MODO[1:0] <= 2'b01;
      #1 ENB <= 1'b0;
			//Enviando flancos activos en CLK
			#8 ;

        //Prueba #5 rotacion circular a la derecha
		    //Establece modo de Carga en Paralelo
    /*  #1 ENB <= 1'b1;
  		#1 MODO[1:0] <= 2'b10;
			DIR <= 1'b1;
			S_IN <= 1'b1;
			//D[3:0] <= 4'b0000; //Ya se probo en las pruebas anteriores
			D[3:0] <= 4'b0001;
			#2D[3:0] <= 4'b0010; //Cambiando Valor
      #2D[3:0] <= 4'b0011; //Cambiando Valor
			#2D[3:0] <= 4'b0100; //Cambiando Valor
			#2D[3:0] <= 4'b0101; //Cambiando Valor
			#2D[3:0] <= 4'b0111; //Cambiando Valor
			#2D[3:0] <= 4'b1000; //Cambiando Valor
			#2D[3:0] <= 4'b1001; //Cambiando Valor
			//D[3:0] <= 4'b1010; //Ya se probo en las pruebas anteriores
			//D[3:0] <= 4'b1011; //Ya se probo en las pruebas anteriores
			#2D[3:0] <= 4'b1100; //Cambiando Valor
			//D[3:0] <= 4'b1101; //Ya se probo en las pruebas anteriores
			#2D[3:0] <= 4'b1110; //Cambiando Valor
			#2D[3:0] <= 4'b1111; //Cambiando Valor
			//Ciclo extra para ver ultimo cambio
*/
		    #10 $finish;
		end
endmodule

Tarea2/mux.v
module  mux(din_0, din_1 , d, out);

    input din_0, din_1, d;
    output wire out;

    assign out = (d) ? din_1 : din_0;

endmodule

Tarea4/reg_desp.v
module reg_desp(Q, S_OUT, CLK, ENB, DIR, S_IN, MODO, D);
    //Declaracion de entradas y salidas
    input CLK, ENB, DIR, S_IN;
    input [1:0] MODO;
    input [3:0] D;
    output reg [3:0] Q;
    output reg S_OUT;

    //registro temporarl para el modo
	  reg [1:0] MODO_TEMP;

  initial begin
    Q[3:0] <= 0;
  end
//Verificacion de habilitacion de lectura del modo
always @(MODO) begin
        if (ENB == 1'b1) begin
			        MODO_TEMP <= MODO;
          end
		    else begin
			        MODO_TEMP <= MODO_TEMP;
        end
  end

  always @(posedge CLK) begin
      case (MODO_TEMP)
        2'b0: //Desp Izquierda
             if (DIR == 1'b0) begin
                  Q <= {Q[2:0],S_IN};
                  S_OUT <= Q[3];
              end
              else begin //Desp derecha
                  Q <= {S_IN,Q[3:1]};
                  S_OUT <= Q[0];
              end
        2'b1: //Rotacion izq
             if (DIR == 1'b0) begin
			            Q <= {Q[2:0],Q[3]};
              end
	    	    	else begin //Rotacion derecha
                  Q <= {Q[0],Q[3:1]};
              end
        2'b10: //Carga en paralelo
             Q[3:0] <= D[3:0];
      endcase
	end

endmodule

Tarea2/reg8.v
`include "reg_desp.v"
`include "mux.v"

module reg8 (Q8, S_OUT8, CLK8, ENB8, DIR8, S_IN8, MODO8, D8);

    input CLK8, ENB8, DIR8, S_IN8;
    input [1:0] MODO8;
    input [7:0] D8;
    output [7:0] Q8;
    output S_OUT8;

    wire wR8SIN, wR8Q0, wR8Q3;
    wire wR1SIN, wR1Q0, wR1Q3;
    wire [7:0] wQ8, wD8;
    wire [1:0] wMODO8;
    wire wS_OUT8, wCLK8, wENB8, wDIR8, wS_IN8;

    assign Q8[7:0] = wQ8[7:0];
    assign S_OUT8 = wS_OUT8;
    assign wCLK8 = CLK8;
    assign wENB8 = ENB8;
    assign wDIR8 = DIR8;
    assign wS_IN8 = S_IN8;
    assign wMODO8 = MODO8;
    assign wD8 = D8;

    assign wR8Q0 = wQ8[0];
    assign wR8Q3 = wQ8[3];
    assign wR1Q0 = wQ8[4];
    assign wR1Q3 = wQ8[7];


    reg_desp reg1(wQ8[7:4], , wCLK8, wENB8, wDIR8, wR1SIN, wMODO8, wD8[7:4]);
    reg_desp reg8(wQ8[3:0], , wCLK8, wENB8, wDIR8, wR8SIN, wMODO8, wD8[3:0]);
    mux mux1(wR8Q3, wS_IN8, wDIR8, wR1SIN);
    mux mux8(wS_IN8, wR1Q0, wDIR8, wR8SIN);
    mux muxOUT(wR1Q3, wR8Q0, wDIR8, wS_OUT8);

  endmodule

Tarea2/testbench8.v
//`include "reg_desp_32.v"

module test_bench;

  wire S_OUT8, CLK8, ENB8, DIR8, S_IN8;
	wire [7:0] Q8, D8;
	wire [1:0] MODO8;

	reg8 registro8(Q8, S_OUT8, CLK8, ENB8, DIR8, S_IN8, MODO8, D8);
  probador8 prueba(Q8, S_OUT8, CLK8, ENB8, DIR8, S_IN8, MODO8, D8);

	initial
	    begin
		    $dumpfile("registro8.vcd");
			$dumpvars;
		end

endmodule

Tarea2/registro8.vcd
$date
	Fri Mar 31 22:21:38 2017
$end
$version
	Icarus Verilog
$end
$timescale
	1s
$end
$scope module test_bench $end
$var wire 1 ! CLK8 $end
$var wire 8 " D8 [7:0] $end
$var wire 1 # DIR8 $end
$var wire 1 $ ENB8 $end
$var wire 2 % MODO8 [1:0] $end
$var wire 8 & Q8 [7:0] $end
$var wire 1 ' S_IN8 $end
$var wire 1 ( S_OUT8 $end
$scope module registro8 $end
$var wire 1 ! CLK8 $end
$var wire 8 ) D8 [7:0] $end
$var wire 1 # DIR8 $end
$var wire 1 $ ENB8 $end
$var wire 2 * MODO8 [1:0] $end
$var wire 8 + Q8 [7:0] $end
$var wire 1 ' S_IN8 $end
$var wire 1 ( S_OUT8 $end
$var wire 1 , wCLK8 $end
$var wire 8 - wD8 [7:0] $end
$var wire 1 . wDIR8 $end
$var wire 1 / wENB8 $end
$var wire 2 0 wMODO8 [1:0] $end
$var wire 8 1 wQ8 [7:0] $end
$var wire 1 2 wR1Q0 $end
$var wire 1 3 wR1Q3 $end
$var wire 1 4 wR1SIN $end
$var wire 1 5 wR8Q0 $end
$var wire 1 6 wR8Q3 $end
$var wire 1 7 wR8SIN $end
$var wire 1 8 wS_IN8 $end
$var wire 1 9 wS_OUT8 $end
$scope module reg1 $end
$var wire 1 , CLK $end
$var wire 4 : D [3:0] $end
$var wire 1 . DIR $end
$var wire 1 / ENB $end
$var wire 2 ; MODO [1:0] $end
$var wire 1 4 S_IN $end
$var reg 2 < MODO_TEMP [1:0] $end
$var reg 4 = Q [3:0] $end
$var reg 1 > S_OUT $end
$upscope $end
$scope module reg8 $end
$var wire 1 , CLK $end
$var wire 4 ? D [3:0] $end
$var wire 1 . DIR $end
$var wire 1 / ENB $end
$var wire 2 @ MODO [1:0] $end
$var wire 1 7 S_IN $end
$var reg 2 A MODO_TEMP [1:0] $end
$var reg 4 B Q [3:0] $end
$var reg 1 C S_OUT $end
$upscope $end
$scope module mux1 $end
$var wire 1 . d $end
$var wire 1 6 din_0 $end
$var wire 1 8 din_1 $end
$var wire 1 4 out $end
$upscope $end
$scope module mux8 $end
$var wire 1 . d $end
$var wire 1 8 din_0 $end
$var wire 1 2 din_1 $end
$var wire 1 7 out $end
$upscope $end
$scope module muxOUT $end
$var wire 1 . d $end
$var wire 1 3 din_0 $end
$var wire 1 5 din_1 $end
$var wire 1 9 out $end
$upscope $end
$upscope $end
$scope module prueba $end
$var wire 8 D Q [7:0] $end
$var wire 1 ( S_OUT $end
$var reg 1 E CLK $end
$var reg 8 F D [7:0] $end
$var reg 1 G DIR $end
$var reg 1 H ENB $end
$var reg 2 I MODO [1:0] $end
$var reg 1 J S_IN $end
$upscope $end
$upscope $end
$enddefinitions $end
#0
$dumpvars
xJ
bx I
1H
xG
bx F
0E
b0 D
xC
b0 B
bx A
bx @
bx ?
x>
b0 =
bx <
bx ;
bx :
09
x8
x7
06
05
x4
03
02
b0 1
bx 0
1/
x.
bx -
0,
b0 +
bx *
bx )
0(
x'
b0 &
bx %
1$
x#
bx "
0!
$end
#1
b10 A
b10 <
b0 :
b1111 ?
04
07
b1111 F
b1111 -
b1111 "
b1111 )
0J
08
0'
0G
0.
0#
b10 I
b10 0
b10 ;
b10 @
b10 %
b10 *
1E
1,
1!
#2
0E
0,
0!
#3
b0 <
b0 A
14
15
16
b1111 B
b1111 &
b1111 +
b1111 D
b1111 1
b0 I
b0 0
b0 ;
b0 @
b0 %
b0 *
1E
1,
1!
#4
0H
0/
0$
0E
0,
0!
#5
12
05
0>
b1 =
1C
b1110 B
b11110 &
b11110 +
b11110 D
b11110 1
1E
1,
1!
#6
0E
0,
0!
#7
b1100 B
b11 =
b111100 &
b111100 +
b111100 D
b111100 1
1E
1,
1!
#8
0E
0,
0!
#9
b111 =
b1000 B
b1111000 &
b1111000 +
b1111000 D
b1111000 1
1E
1,
1!
#10
0E
0,
0!
#11
04
19
1(
06
13
b0 B
b1111 =
b11110000 &
b11110000 +
b11110000 D
b11110000 1
1E
1,
1!
#12
0E
0,
0!
#13
02
1>
b1110 =
b11100000 &
b11100000 +
b11100000 D
b11100000 1
0C
1H
1/
1$
1E
1,
1!
#14
0E
0,
0!
#15
b10 A
b10 <
14
09
0(
b1100 =
b11000000 &
b11000000 +
b11000000 D
b11000000 1
1J
18
1'
1G
1.
1#
b10 I
b10 0
b10 ;
b10 @
b10 %
b10 *
1E
1,
1!
#16
0E
0,
0!
#17
b0 <
b0 A
19
1(
03
15
16
b0 =
b1111 B
b1111 &
b1111 +
b1111 D
b1111 1
b0 I
b0 0
b0 ;
b0 @
b0 %
b0 *
1E
1,
1!
#18
0H
0/
0$
0E
0,
0!
#19
06
13
1C
b111 B
0>
b1000 =
b10000111 &
b10000111 +
b10000111 D
b10000111 1
1E
1,
1!
#20
0E
0,
0!
#21
b1100 =
b11 B
b11000011 &
b11000011 +
b11000011 D
b11000011 1
1E
1,
1!
#22
0E
0,
0!
#23
b1 B
b1110 =
b11100001 &
b11100001 +
b11100001 D
b11100001 1
1E
1,
1!
#24
0E
0,
0!
#25
17
09
0(
12
05
b1111 =
b0 B
b11110000 &
b11110000 +
b11110000 D
b11110000 1
1E
1,
1!
#26
0E
0,
0!
#27
16
0C
b1000 B
b11111000 &
b11111000 +
b11111000 D
b11111000 1
1>
1H
1/
1$
1E
1,
1!
#28
0E
0,
0!
#29
b10 A
b10 <
b1111 :
b0 ?
19
1(
b1100 B
b11111100 &
b11111100 +
b11111100 D
b11111100 1
b11110000 F
b11110000 -
b11110000 "
b11110000 )
0G
0.
0#
b10 I
b10 0
b10 ;
b10 @
b10 %
b10 *
1E
1,
1!
#30
0E
0,
0!
#31
b1 <
b1 A
04
06
b0 B
b11110000 &
b11110000 +
b11110000 D
b11110000 1
b1 I
b1 0
b1 ;
b1 @
b1 %
b1 *
1E
1,
1!
#32
0H
0/
0$
0E
0,
0!
#33
1E
1,
1!
#34
0E
0,
0!
#35
1E
1,
1!
#36
0E
0,
0!
#37
1E
1,
1!
#38
0E
0,
0!
#39
1E
1,
1!
#40
0E
0,
0!
#41
1H
1/
1$
1E
1,
1!
#42
0E
0,
0!
#43
b10 A
b10 <
b0 :
b1111 ?
14
09
0(
b1111 F
b1111 -
b1111 "
b1111 )
1G
1.
1#
b10 I
b10 0
b10 ;
b10 @
b10 %
b10 *
1E
1,
1!
#44
0E
0,
0!
#45
b1 <
b1 A
07
19
1(
02
03
15
16
b0 =
b1111 B
b1111 &
b1111 +
b1111 D
b1111 1
b1 I
b1 0
b1 ;
b1 @
b1 %
b1 *
1E
1,
1!
#46
0H
0/
0$
0E
0,
0!
