Tarea2/probador.v
module probador(Q, S_OUT, CLK, ENB, DIR, S_IN, MODO, D);

    output reg CLK, ENB, DIR, S_IN;
    output reg [1:0] MODO;
    output reg [3:0] D;
    input [3:0] Q;
    input S_OUT;
    // Configuracion del reloj
		initial begin
				CLK = 0;
		end

		always begin
				#1 CLK = ~CLK;
		end

	initial begin
		//Prueba #1 rotacion a la izquierda
		    //Habilita lectura del modo
			ENB <= 1'b1;
		    //Establece modo de Carga en Paralelo
		  #1 MODO[1:0] <= 2'b10;
			DIR <= 1'b0;
		  S_IN <= 1'b1;
			D[3:0] <= 4'b0;
			//Pone modo de rotacion, como DIR=0 es a la izquierda
			#1 MODO[1:0] <= 2'b0;
      #1 ENB <= 1'b0;
			//Enviar 4 flancos activos en CLK, luego da otros flancos para percibir salida final de S_OUT
			#8 ;

		//Prueba #2 rotacion a la derecha
		    //Establece modo de Carga en Paralelo
      #1 ENB <= 1'b1;
		  #2 MODO[1:0] <= 2'b10;
			DIR <= 1'b1;
			S_IN <= 1'b0;
			D[3:0] <= 4'b1010;
			//Pone modo de rotacion, como DIR=1 es a la derecha
			#1 MODO[1:0] <= 2'b0;
      #1 ENB <= 1'b0;
			//Enviando flancos activos en CLK
			#8 ;

		//Prueba #3 rotacion circular a la izquierda
		    //Establece modo de Carga en Paralelo
      #1 ENB <= 1'b1;
      #1 MODO[1:0] <= 2'b10;
			DIR <= 1'b0;
			S_IN <= 1'b1;
			D[3:0] <= 4'b1011;
			//Pone modo de rotacion, como DIR=0 es a la izquierda
			#1 MODO[1:0] <= 2'b01;
      #1 ENB <= 1'b0;
			//Enviando flancos activos en CLK
			#8 ;

        //Prueba #4 rotacion circular a la derecha
		    //Establece modo de Carga en Paralelo
      #1 ENB <= 1'b1;
  		#2 MODO[1:0] <= 2'b10;
			DIR <= 1'b1;
			S_IN <= 1'b1;
			D[3:0] <= 4'b1101;
			//Pone modo de rotacion, como DIR=1 es a la derecha
			#1 MODO[1:0] <= 2'b01;
      #1 ENB <= 1'b0;
			//Enviando flancos activos en CLK
			#8 ;

        //Prueba #5 rotacion circular a la derecha
		    //Establece modo de Carga en Paralelo
      #1 ENB <= 1'b1;
  		#1 MODO[1:0] <= 2'b10;
			DIR <= 1'b1;
			S_IN <= 1'b1;
			//D[3:0] <= 4'b0000; //Ya se probo en las pruebas anteriores
			D[3:0] <= 4'b0001;
			#2D[3:0] <= 4'b0010; //Cambiando Valor
      #2D[3:0] <= 4'b0011; //Cambiando Valor
			#2D[3:0] <= 4'b0100; //Cambiando Valor
			#2D[3:0] <= 4'b0101; //Cambiando Valor
			#2D[3:0] <= 4'b0111; //Cambiando Valor
			#2D[3:0] <= 4'b1000; //Cambiando Valor
			#2D[3:0] <= 4'b1001; //Cambiando Valor
			//D[3:0] <= 4'b1010; //Ya se probo en las pruebas anteriores
			//D[3:0] <= 4'b1011; //Ya se probo en las pruebas anteriores
			#2D[3:0] <= 4'b1100; //Cambiando Valor
			//D[3:0] <= 4'b1101; //Ya se probo en las pruebas anteriores
			#2D[3:0] <= 4'b1110; //Cambiando Valor
			#2D[3:0] <= 4'b1111; //Cambiando Valor
			//Ciclo extra para ver ultimo cambio

		    #10 $finish;
		end
endmodule

Tarea4/reg_desp.v
module reg_desp(Q, S_OUT, CLK, ENB, DIR, S_IN, MODO, D);
    //Declaracion de entradas y salidas
    input CLK, ENB, DIR, S_IN;
    input [1:0] MODO;
    input [3:0] D;
    output reg [3:0] Q;
    output reg S_OUT;

    //registro temporarl para el modo
	  reg [1:0] MODO_TEMP;

  initial begin
    Q[3:0] <= 0;
  end
//Verificacion de habilitacion de lectura del modo
always @(MODO) begin
        if (ENB == 1'b1) begin
			        MODO_TEMP <= MODO;
          end
		    else begin
			        MODO_TEMP <= MODO_TEMP;
        end
  end

  always @(posedge CLK) begin
      case (MODO_TEMP)
        2'b0: //Desp Izquierda
             if (DIR == 1'b0) begin
                  Q <= {Q[2:0],S_IN};
                  S_OUT <= Q[3];
              end
              else begin //Desp derecha
                  Q <= {S_IN,Q[3:1]};
                  S_OUT <= Q[0];
              end
        2'b1: //Rotacion izq
             if (DIR == 1'b0) begin
			            Q <= {Q[2:0],Q[3]};
              end
	    	    	else begin //Rotacion derecha
                  Q <= {Q[0],Q[3:1]};
              end
        2'b10: //Carga en paralelo
             Q[3:0] <= D[3:0];
      endcase
	end

endmodule

Tarea2/test_bench.v
//`include "reg_desp.v"

module test_bench;


  wire S_OUT, CLK, ENB, DIR, S_IN;
	wire [3:0] Q, D;
	wire [1:0] MODO;

	reg_desp reg4(Q, S_OUT, CLK, ENB, DIR, S_IN, MODO, D);
	probador prueba4(Q, S_OUT, CLK, ENB, DIR, S_IN, MODO, D);

	initial
	    begin
		    $dumpfile("registro4.vcd");
			$dumpvars;
		end

endmodule

Tarea2/registro4.vcd
$date
	Sat Apr  1 00:40:23 2017
$end
$version
	Icarus Verilog
$end
$timescale
	1s
$end
$scope module test_bench $end
$var wire 1 ! CLK $end
$var wire 4 " D [3:0] $end
$var wire 1 # DIR $end
$var wire 1 $ ENB $end
$var wire 2 % MODO [1:0] $end
$var wire 4 & Q [3:0] $end
$var wire 1 ' S_IN $end
$var wire 1 ( S_OUT $end
$scope module reg4 $end
$var wire 1 ! CLK $end
$var wire 4 ) D [3:0] $end
$var wire 1 # DIR $end
$var wire 1 $ ENB $end
$var wire 2 * MODO [1:0] $end
$var wire 1 ' S_IN $end
$var reg 2 + MODO_TEMP [1:0] $end
$var reg 4 , Q [3:0] $end
$var reg 1 - S_OUT $end
$upscope $end
$scope module prueba4 $end
$var wire 4 . Q [3:0] $end
$var wire 1 ( S_OUT $end
$var reg 1 / CLK $end
$var reg 4 0 D [3:0] $end
$var reg 1 1 DIR $end
$var reg 1 2 ENB $end
$var reg 2 3 MODO [1:0] $end
$var reg 1 4 S_IN $end
$upscope $end
$upscope $end
$enddefinitions $end
#0
$dumpvars
x4
bx 3
12
x1
bx 0
0/
b0 .
x-
b0 ,
bx +
bx *
bx )
x(
x'
b0 &
bx %
1$
x#
bx "
0!
$end
#1
b10 +
b0 0
b0 "
b0 )
14
1'
01
0#
b10 3
b10 %
b10 *
1/
1!
#2
b0 +
b0 3
b0 %
b0 *
0/
0!
#3
0-
0(
b1 ,
b1 &
b1 .
02
0$
1/
1!
#4
0/
0!
#5
b11 ,
b11 &
b11 .
1/
1!
#6
0/
0!
#7
b111 ,
b111 &
b111 .
1/
1!
#8
0/
0!
#9
b1111 ,
b1111 &
b1111 .
1/
1!
#10
0/
0!
#11
1-
1(
1/
1!
#12
12
1$
0/
0!
#13
1/
1!
#14
b10 +
b1010 0
b1010 "
b1010 )
04
0'
11
1#
b10 3
b10 %
b10 *
0/
0!
#15
b0 +
b1010 ,
b1010 &
b1010 .
b0 3
b0 %
b0 *
1/
1!
#16
02
0$
0/
0!
#17
0-
0(
b101 ,
b101 &
b101 .
1/
1!
#18
0/
0!
#19
1-
1(
b10 ,
b10 &
b10 .
1/
1!
#20
0/
0!
#21
0-
0(
b1 ,
b1 &
b1 .
1/
1!
#22
0/
0!
#23
1-
1(
b0 ,
b0 &
b0 .
1/
1!
#24
0/
0!
#25
0-
0(
12
1$
1/
1!
#26
b10 +
b1011 0
b1011 "
b1011 )
14
1'
01
0#
b10 3
b10 %
b10 *
0/
0!
#27
b1 +
b1011 ,
b1011 &
b1011 .
b1 3
b1 %
b1 *
1/
1!
#28
02
0$
0/
0!
#29
b111 ,
b111 &
b111 .
1/
1!
#30
0/
0!
#31
b1110 ,
b1110 &
b1110 .
1/
1!
#32
0/
0!
#33
b1101 ,
b1101 &
b1101 .
1/
1!
#34
0/
0!
#35
b1011 ,
b1011 &
b1011 .
1/
1!
#36
0/
0!
#37
b111 ,
b111 &
b111 .
12
1$
1/
1!
#38
0/
0!
#39
b10 +
b1110 ,
b1110 &
b1110 .
b1101 0
b1101 "
b1101 )
11
1#
b10 3
b10 %
b10 *
1/
1!
#40
b1 +
b1 3
b1 %
b1 *
0/
0!
#41
b111 ,
b111 &
b111 .
02
0$
1/
1!
#42
0/
0!
#43
b1011 ,
b1011 &
b1011 .
1/
1!
#44
0/
0!
#45
b1101 ,
b1101 &
b1101 .
1/
1!
#46
0/
0!
#47
b1110 ,
b1110 &
b1110 .
1/
1!
#48
0/
0!
#49
b111 ,
b111 &
b111 .
1/
1!
#50
12
1$
0/
0!
#51
b10 +
b1011 ,
b1011 &
b1011 .
b1 0
b1 "
b1 )
b10 3
b10 %
b10 *
1/
1!
#52
0/
0!
#53
b1 ,
b1 &
b1 .
b10 0
b10 "
b10 )
1/
1!
#54
0/
0!
#55
b10 ,
b10 &
b10 .
b11 0
b11 "
b11 )
1/
1!
#56
0/
0!
#57
b11 ,
b11 &
b11 .
b100 0
b100 "
b100 )
1/
1!
#58
0/
0!
#59
b100 ,
b100 &
b100 .
b101 0
b101 "
b101 )
1/
1!
#60
0/
0!
#61
b101 ,
b101 &
b101 .
b111 0
b111 "
b111 )
1/
1!
#62
0/
0!
#63
b111 ,
b111 &
b111 .
b1000 0
b1000 "
b1000 )
1/
1!
#64
0/
0!
#65
b1000 ,
b1000 &
b1000 .
b1001 0
b1001 "
b1001 )
1/
1!
#66
0/
0!
#67
b1001 ,
b1001 &
b1001 .
b1100 0
b1100 "
b1100 )
1/
1!
#68
0/
0!
#69
b1100 ,
b1100 &
b1100 .
b1110 0
b1110 "
b1110 )
1/
1!
#70
0/
0!
#71
b1110 ,
b1110 &
b1110 .
b1111 0
b1111 "
b1111 )
1/
1!
#72
0/
0!
#73
b1111 ,
b1111 &
b1111 .
1/
1!
